<v:view 
	xmlns="http://www.w3.org/1999/xhtml" 
	xmlns:v="http://www.cruxframework.org/view"
	xmlns:core="http://www.cruxframework.org/crux" 
	xmlns:crux="http://www.cruxframework.org/crux/widgets"
	xmlns:gwt="http://www.cruxframework.org/crux/gwt" 
	xmlns:showcase="http://www.cruxframework.org/templates/showcase"
	title="My Orders">

	<center>
		<gwt:HTMLPanel id="parentPanel" styleName="topMenuDisposalPanel">
			<gwt:HTMLPanel id="panelLabel" styleName="topMenuDisposalPanelLeft">
				<gwt:label id="labelTitle" text="My Orders" styleName="topMenuDisposalTitle"/>
				<gwt:label id="labelInfo" text="View order details" styleName="topMenuDisposalInfo"/>
			</gwt:HTMLPanel>
		
			<br />
			<crux:styledPanel id="panelList" styleName="topMenuDisposalPanelList">
				<gwt:label id="labelPurchase" text="Wish List" styleName="topMenuDisposalListInactive"/>
			</crux:styledPanel>
		</gwt:HTMLPanel>
	</center>

</v:view>